py_redux-0.2.2.dist-info/DESCRIPTION.rst
py_redux-0.2.2.dist-info/METADATA
py_redux-0.2.2.dist-info/RECORD
py_redux-0.2.2.dist-info/WHEEL
py_redux-0.2.2.dist-info/metadata.json
py_redux-0.2.2.dist-info/top_level.txt
redux/__init__.py
redux/apply_middleware.py
redux/bind_action_creators.py
redux/combine_reducers.py
redux/compose.py
redux/create_store.py
redux/middlewares.py
