Metadata-Version: 2.0
Name: py-redux
Version: 0.2.2
Summary: python implementation of the redux library
Home-page: https://github.com/emersonknapp/pyredux
Author: Emerson Knapp
Author-email: emerson.b.knapp@gmail.com
License: MIT
Keywords: redux development state ui
Platform: UNKNOWN
Classifier: Development Status :: 3 - Alpha
Classifier: Intended Audience :: Developers
Classifier: License :: OSI Approved :: MIT License
Classifier: Programming Language :: Python :: 2.7
Requires-Dist: frozendict
